nlweb_snowflake_vectordb/__init__.py
nlweb_snowflake_vectordb/snowflake_cortex_client.py
nlweb_snowflake_vectordb-0.5.42.dist-info/METADATA
nlweb_snowflake_vectordb-0.5.42.dist-info/WHEEL
nlweb_snowflake_vectordb-0.5.42.dist-info/top_level.txt
nlweb_snowflake_vectordb-0.5.42.dist-info/RECORD
