Metadata-Version: 2.4
Name: nlweb-snowflake-vectordb
Version: 0.5.42
Summary: Snowflake Cortex Search vector database provider for NLWeb
Author-email: NLWeb AI <info@nlweb.ai>
License: MIT
Project-URL: Homepage, https://github.com/nlweb-ai/NLWeb_Core
Project-URL: Repository, https://github.com/nlweb-ai/NLWeb_Core
Project-URL: Documentation, https://github.com/nlweb-ai/NLWeb_Core/tree/main/packages/providers/snowflake/vectordb
Keywords: nlweb,snowflake,cortex,vector-database,search
Classifier: Development Status :: 4 - Beta
Classifier: Intended Audience :: Developers
Classifier: License :: OSI Approved :: MIT License
Classifier: Programming Language :: Python :: 3
Classifier: Programming Language :: Python :: 3.10
Classifier: Programming Language :: Python :: 3.11
Classifier: Programming Language :: Python :: 3.12
Requires-Python: >=3.10
Requires-Dist: nlweb-core>=0.5.4
Requires-Dist: httpx>=0.28.1
Provides-Extra: dev
Requires-Dist: pytest>=7.0.0; extra == "dev"
Requires-Dist: pytest-asyncio>=0.21.0; extra == "dev"
Requires-Dist: pytest-cov>=4.0.0; extra == "dev"
Requires-Dist: pytest-mock>=3.10.0; extra == "dev"
